.gitignore
CHANGES.rst
Dockerfile
MANIFEST.in
Makefile
README.rst
bootstrap.py
buildout.cfg
docker-buildout.cfg
docker-compose.yml
docker-entrypoint.sh
setup.py
docs/INSTALL.txt
docs/LICENSE.GPL
docs/LICENSE.txt
src/collective/__init__.py
src/collective.z3cform.mapwidget.egg-info/PKG-INFO
src/collective.z3cform.mapwidget.egg-info/SOURCES.txt
src/collective.z3cform.mapwidget.egg-info/dependency_links.txt
src/collective.z3cform.mapwidget.egg-info/entry_points.txt
src/collective.z3cform.mapwidget.egg-info/namespace_packages.txt
src/collective.z3cform.mapwidget.egg-info/not-zip-safe
src/collective.z3cform.mapwidget.egg-info/requires.txt
src/collective.z3cform.mapwidget.egg-info/top_level.txt
src/collective/z3cform/__init__.py
src/collective/z3cform/mapwidget/__init__.py
src/collective/z3cform/mapwidget/configure.zcml
src/collective/z3cform/mapwidget/field.py
src/collective/z3cform/mapwidget/map_display.pt
src/collective/z3cform/mapwidget/map_input.pt
src/collective/z3cform/mapwidget/widget.py
src/collective/z3cform/mapwidget/demo/__init__.py
src/collective/z3cform/mapwidget/demo/browser.py
src/collective/z3cform/mapwidget/demo/configure.zcml
src/collective/z3cform/mapwidget/locales/collective.z3cform.mapwidget.pot
src/collective/z3cform/mapwidget/locales/rebuild.sh
src/collective/z3cform/mapwidget/locales/de/LC_MESSAGES/collective.z3cform.mapwidget.po
src/collective/z3cform/mapwidget/locales/it/LC_MESSAGES/collective.z3cform.mapwidget.po
src/collective/z3cform/mapwidget/locales/zh_CN/LC_MESSAGES/collective.z3cform.mapwidget.po
src/collective/z3cform/mapwidget/profiles/default/metadata.xml