Metadata-Version: 1.1
Name: collective.z3cform.mapwidget
Version: 2.2
Summary: z3c.form map widget
Home-page: http://www.coactivate.org/projects/collectivegeo/project-home
Author: collective.geo Project
Author-email: collectivegeo-discussion@lists.coactivate.org
License: GPL
Keywords: z3c.form form widget collective.geo map OpenLayers
Platform: UNKNOWN
Classifier: Framework :: Plone
Classifier: Programming Language :: Python
